{
    "os": "Linux-5.15.133.1-microsoft-standard-WSL2-x86_64-with-glibc2.35",
    "python": "3.9.18",
    "heartbeatAt": "2023-11-24T03:38:06.983651",
    "startedAt": "2023-11-24T03:38:06.228579",
    "docker": null,
    "cuda": null,
    "args": [
        ".",
        "-vv",
        "--csv",
        "clean_sample.csv:latest",
        "--ref",
        "clean_sample.csv:reference",
        "--kl_threshold",
        "0.2",
        "--min_price",
        "10",
        "--max_price",
        "350"
    ],
    "state": "running",
    "program": "/home/indigon/miniconda3/envs/mlflow-af6473294b18f57ea960125076520147a7a4be59/bin/pytest",
    "git": {
        "remote": "https://github.com/INDIG0N/Project-Build-an-ML-Pipeline-Starter.git",
        "commit": "de35e093556231566852c2be0d98990e7ef7a163"
    },
    "email": "hicksjordan1999@gmail.com",
    "root": "/home/indigon/projects/Project-Build-an-ML-Pipeline-Starter",
    "host": "DESKTOP-N061D2H",
    "username": "indigon",
    "executable": "/home/indigon/miniconda3/envs/mlflow-af6473294b18f57ea960125076520147a7a4be59/bin/python",
    "cpu_count": 8,
    "cpu_count_logical": 16,
    "cpu_freq": {
        "current": 3393.679000000001,
        "min": 0.0,
        "max": 0.0
    },
    "cpu_freq_per_core": [
        {
            "current": 3393.679,
            "min": 0.0,
            "max": 0.0
        },
        {
            "current": 3393.679,
            "min": 0.0,
            "max": 0.0
        },
        {
            "current": 3393.679,
            "min": 0.0,
            "max": 0.0
        },
        {
            "current": 3393.679,
            "min": 0.0,
            "max": 0.0
        },
        {
            "current": 3393.679,
            "min": 0.0,
            "max": 0.0
        },
        {
            "current": 3393.679,
            "min": 0.0,
            "max": 0.0
        },
        {
            "current": 3393.679,
            "min": 0.0,
            "max": 0.0
        },
        {
            "current": 3393.679,
            "min": 0.0,
            "max": 0.0
        },
        {
            "current": 3393.679,
            "min": 0.0,
            "max": 0.0
        },
        {
            "current": 3393.679,
            "min": 0.0,
            "max": 0.0
        },
        {
            "current": 3393.679,
            "min": 0.0,
            "max": 0.0
        },
        {
            "current": 3393.679,
            "min": 0.0,
            "max": 0.0
        },
        {
            "current": 3393.679,
            "min": 0.0,
            "max": 0.0
        },
        {
            "current": 3393.679,
            "min": 0.0,
            "max": 0.0
        },
        {
            "current": 3393.679,
            "min": 0.0,
            "max": 0.0
        },
        {
            "current": 3393.679,
            "min": 0.0,
            "max": 0.0
        }
    ],
    "disk": {
        "total": 1006.853931427002,
        "used": 12.62283706665039
    },
    "memory": {
        "total": 7.722969055175781
    }
}
